subformer/__init__.py
subformer/client.py
subformer/exceptions.py
subformer/py.typed
subformer/types.py
subformer-0.1.0.dist-info/METADATA
subformer-0.1.0.dist-info/WHEEL
subformer-0.1.0.dist-info/licenses/LICENSE
subformer-0.1.0.dist-info/RECORD
