Metadata-Version: 2.4
Name: subformer
Version: 0.1.0
Summary: Official Python SDK for Subformer - AI-powered video dubbing and voice cloning
Project-URL: Homepage, https://subformer.com
Project-URL: Documentation, https://subformer.com/docs/api
Project-URL: Repository, https://github.com/subformer/subformer-python
Project-URL: Issues, https://github.com/subformer/subformer-python/issues
Author-email: Subformer <support@subformer.com>
License-Expression: MIT
License-File: LICENSE
Keywords: ai,subformer,translation,tts,video-dubbing,voice-cloning
Classifier: Development Status :: 4 - Beta
Classifier: Intended Audience :: Developers
Classifier: License :: OSI Approved :: MIT License
Classifier: Programming Language :: Python :: 3
Classifier: Programming Language :: Python :: 3.8
Classifier: Programming Language :: Python :: 3.9
Classifier: Programming Language :: Python :: 3.10
Classifier: Programming Language :: Python :: 3.11
Classifier: Programming Language :: Python :: 3.12
Classifier: Topic :: Multimedia :: Sound/Audio
Classifier: Topic :: Multimedia :: Video
Classifier: Topic :: Scientific/Engineering :: Artificial Intelligence
Requires-Python: >=3.8
Requires-Dist: httpx>=0.24.0
Requires-Dist: pydantic>=2.0.0
Provides-Extra: dev
Requires-Dist: pytest-asyncio>=0.21.0; extra == 'dev'
Requires-Dist: pytest>=7.0.0; extra == 'dev'
Requires-Dist: ruff>=0.1.0; extra == 'dev'
